{
  "2025-07-08T00:50:00+00:00": {
    "fmizonlib": "Zone G\u00e9n\u00e9rale",
    "fmizonnum": 14,
    "sortie": 0,
    "fmizonmax": 400,
    "entree": 0,
    "etablissement_etalib": "Piscine Grand Parc",
    "fmicourante": 0,
    "datemiseajour": "2025-07-08T00:50:00+00:00"
  },
  "2025-07-08T08:10:00+00:00": {
    "fmizonlib": "Zone G\u00e9n\u00e9rale",
    "fmizonnum": 14,
    "sortie": 0,
    "fmizonmax": 400,
    "entree": 31,
    "etablissement_etalib": "Piscine Grand Parc",
    "fmicourante": 31,
    "datemiseajour": "2025-07-08T08:10:00+00:00"
  },
  "2025-07-08T08:45:00+00:00": {
    "fmizonlib": "Zone G\u00e9n\u00e9rale",
    "fmizonnum": 14,
    "sortie": 2,
    "fmizonmax": 400,
    "entree": 65,
    "etablissement_etalib": "Piscine Grand Parc",
    "fmicourante": 63,
    "datemiseajour": "2025-07-08T08:45:00+00:00"
  },
  "2025-07-08T09:15:00+00:00": {
    "fmizonlib": "Zone G\u00e9n\u00e9rale",
    "fmizonnum": 14,
    "sortie": 15,
    "fmizonmax": 400,
    "entree": 91,
    "etablissement_etalib": "Piscine Grand Parc",
    "fmicourante": 76,
    "datemiseajour": "2025-07-08T09:15:00+00:00"
  },
  "2025-07-08T09:35:00+00:00": {
    "fmizonlib": "Zone G\u00e9n\u00e9rale",
    "fmizonnum": 14,
    "sortie": 36,
    "fmizonmax": 400,
    "entree": 98,
    "etablissement_etalib": "Piscine Grand Parc",
    "fmicourante": 62,
    "datemiseajour": "2025-07-08T09:35:00+00:00"
  },
  "2025-07-08T09:45:00+00:00": {
    "fmizonlib": "Zone G\u00e9n\u00e9rale",
    "fmizonnum": 14,
    "sortie": 41,
    "fmizonmax": 400,
    "entree": 104,
    "etablissement_etalib": "Piscine Grand Parc",
    "fmicourante": 63,
    "datemiseajour": "2025-07-08T09:45:00+00:00"
  },
  "2025-07-08T10:10:00+00:00": {
    "fmizonlib": "Zone G\u00e9n\u00e9rale",
    "fmizonnum": 14,
    "sortie": 62,
    "fmizonmax": 400,
    "entree": 129,
    "etablissement_etalib": "Piscine Grand Parc",
    "fmicourante": 67,
    "datemiseajour": "2025-07-08T10:10:00+00:00"
  },
  "2025-07-08T10:35:00+00:00": {
    "fmizonlib": "Zone G\u00e9n\u00e9rale",
    "fmizonnum": 14,
    "sortie": 95,
    "fmizonmax": 400,
    "entree": 156,
    "etablissement_etalib": "Piscine Grand Parc",
    "fmicourante": 61,
    "datemiseajour": "2025-07-08T10:35:00+00:00"
  },
  "2025-07-08T10:50:00+00:00": {
    "fmizonlib": "Zone G\u00e9n\u00e9rale",
    "fmizonnum": 14,
    "sortie": 101,
    "fmizonmax": 400,
    "entree": 168,
    "etablissement_etalib": "Piscine Grand Parc",
    "fmicourante": 67,
    "datemiseajour": "2025-07-08T10:50:00+00:00"
  },
  "2025-07-08T11:05:00+00:00": {
    "fmizonlib": "Zone G\u00e9n\u00e9rale",
    "fmizonnum": 14,
    "sortie": 109,
    "fmizonmax": 400,
    "entree": 171,
    "etablissement_etalib": "Piscine Grand Parc",
    "fmicourante": 62,
    "datemiseajour": "2025-07-08T11:05:00+00:00"
  },
  "2025-07-08T11:20:00+00:00": {
    "fmizonlib": "Zone G\u00e9n\u00e9rale",
    "fmizonnum": 14,
    "sortie": 134,
    "fmizonmax": 400,
    "entree": 172,
    "etablissement_etalib": "Piscine Grand Parc",
    "fmicourante": 38,
    "datemiseajour": "2025-07-08T11:20:00+00:00"
  },
  "2025-07-08T11:35:00+00:00": {
    "fmizonlib": "Zone G\u00e9n\u00e9rale",
    "fmizonnum": 14,
    "sortie": 152,
    "fmizonmax": 400,
    "entree": 172,
    "etablissement_etalib": "Piscine Grand Parc",
    "fmicourante": 20,
    "datemiseajour": "2025-07-08T11:35:00+00:00"
  },
  "2025-07-08T11:40:00+00:00": {
    "fmizonlib": "Zone G\u00e9n\u00e9rale",
    "fmizonnum": 14,
    "sortie": 165,
    "fmizonmax": 400,
    "entree": 172,
    "etablissement_etalib": "Piscine Grand Parc",
    "fmicourante": 7,
    "datemiseajour": "2025-07-08T11:40:00+00:00"
  },
  "2025-07-08T12:25:00+00:00": {
    "fmizonlib": "Zone G\u00e9n\u00e9rale",
    "fmizonnum": 14,
    "sortie": 172,
    "fmizonmax": 400,
    "entree": 172,
    "etablissement_etalib": "Piscine Grand Parc",
    "fmicourante": 0,
    "datemiseajour": "2025-07-08T12:25:00+00:00"
  },
  "2025-07-08T13:40:00+00:00": {
    "fmizonlib": "Zone G\u00e9n\u00e9rale",
    "fmizonnum": 14,
    "sortie": 173,
    "fmizonmax": 400,
    "entree": 262,
    "etablissement_etalib": "Piscine Grand Parc",
    "fmicourante": 89,
    "datemiseajour": "2025-07-08T13:40:00+00:00"
  },
  "2025-07-08T14:05:00+00:00": {
    "fmizonlib": "Zone G\u00e9n\u00e9rale",
    "fmizonnum": 14,
    "sortie": 176,
    "fmizonmax": 400,
    "entree": 278,
    "etablissement_etalib": "Piscine Grand Parc",
    "fmicourante": 102,
    "datemiseajour": "2025-07-08T14:05:00+00:00"
  },
  "2025-07-08T14:30:00+00:00": {
    "fmizonlib": "Zone G\u00e9n\u00e9rale",
    "fmizonnum": 14,
    "sortie": 196,
    "fmizonmax": 400,
    "entree": 308,
    "etablissement_etalib": "Piscine Grand Parc",
    "fmicourante": 112,
    "datemiseajour": "2025-07-08T14:30:00+00:00"
  },
  "2025-07-08T14:50:00+00:00": {
    "fmizonlib": "Zone G\u00e9n\u00e9rale",
    "fmizonnum": 14,
    "sortie": 220,
    "fmizonmax": 400,
    "entree": 317,
    "etablissement_etalib": "Piscine Grand Parc",
    "fmicourante": 97,
    "datemiseajour": "2025-07-08T14:50:00+00:00"
  },
  "2025-07-08T15:05:00+00:00": {
    "fmizonlib": "Zone G\u00e9n\u00e9rale",
    "fmizonnum": 14,
    "sortie": 227,
    "fmizonmax": 400,
    "entree": 332,
    "etablissement_etalib": "Piscine Grand Parc",
    "fmicourante": 105,
    "datemiseajour": "2025-07-08T15:05:00+00:00"
  },
  "2025-07-08T15:30:00+00:00": {
    "fmizonlib": "Zone G\u00e9n\u00e9rale",
    "fmizonnum": 14,
    "sortie": 247,
    "fmizonmax": 400,
    "entree": 354,
    "etablissement_etalib": "Piscine Grand Parc",
    "fmicourante": 107,
    "datemiseajour": "2025-07-08T15:30:00+00:00"
  },
  "2025-07-08T15:45:00+00:00": {
    "fmizonlib": "Zone G\u00e9n\u00e9rale",
    "fmizonnum": 14,
    "sortie": 260,
    "fmizonmax": 400,
    "entree": 362,
    "etablissement_etalib": "Piscine Grand Parc",
    "fmicourante": 102,
    "datemiseajour": "2025-07-08T15:45:00+00:00"
  },
  "2025-07-08T16:10:00+00:00": {
    "fmizonlib": "Zone G\u00e9n\u00e9rale",
    "fmizonnum": 14,
    "sortie": 291,
    "fmizonmax": 400,
    "entree": 382,
    "etablissement_etalib": "Piscine Grand Parc",
    "fmicourante": 91,
    "datemiseajour": "2025-07-08T16:10:00+00:00"
  },
  "2025-07-08T16:45:00+00:00": {
    "fmizonlib": "Zone G\u00e9n\u00e9rale",
    "fmizonnum": 14,
    "sortie": 332,
    "fmizonmax": 400,
    "entree": 428,
    "etablissement_etalib": "Piscine Grand Parc",
    "fmicourante": 96,
    "datemiseajour": "2025-07-08T16:45:00+00:00"
  },
  "2025-07-08T17:05:00+00:00": {
    "fmizonlib": "Zone G\u00e9n\u00e9rale",
    "fmizonnum": 14,
    "sortie": 354,
    "fmizonmax": 400,
    "entree": 431,
    "etablissement_etalib": "Piscine Grand Parc",
    "fmicourante": 77,
    "datemiseajour": "2025-07-08T17:05:00+00:00"
  }
}