{
  "2025-02-18T00:50:00+00:00": {
    "fmizonlib": "Zone G\u00e9n\u00e9rale",
    "fmizonnum": 14,
    "sortie": 0,
    "fmizonmax": 400,
    "entree": 0,
    "etablissement_etalib": "Piscine Grand Parc",
    "fmicourante": 0,
    "datemiseajour": "2025-02-18T00:50:00+00:00"
  },
  "2025-02-18T06:40:00+00:00": {
    "fmizonlib": "Zone G\u00e9n\u00e9rale",
    "fmizonnum": 14,
    "sortie": 0,
    "fmizonmax": 400,
    "entree": 24,
    "etablissement_etalib": "Piscine Grand Parc",
    "fmicourante": 24,
    "datemiseajour": "2025-02-18T06:40:00+00:00"
  },
  "2025-02-18T06:45:00+00:00": {
    "fmizonlib": "Zone G\u00e9n\u00e9rale",
    "fmizonnum": 14,
    "sortie": 0,
    "fmizonmax": 400,
    "entree": 27,
    "etablissement_etalib": "Piscine Grand Parc",
    "fmicourante": 27,
    "datemiseajour": "2025-02-18T06:45:00+00:00"
  },
  "2025-02-18T07:10:00+00:00": {
    "fmizonlib": "Zone G\u00e9n\u00e9rale",
    "fmizonnum": 14,
    "sortie": 1,
    "fmizonmax": 400,
    "entree": 33,
    "etablissement_etalib": "Piscine Grand Parc",
    "fmicourante": 32,
    "datemiseajour": "2025-02-18T07:10:00+00:00"
  },
  "2025-02-18T07:20:00+00:00": {
    "fmizonlib": "Zone G\u00e9n\u00e9rale",
    "fmizonnum": 14,
    "sortie": 2,
    "fmizonmax": 400,
    "entree": 34,
    "etablissement_etalib": "Piscine Grand Parc",
    "fmicourante": 32,
    "datemiseajour": "2025-02-18T07:20:00+00:00"
  },
  "2025-02-18T07:30:00+00:00": {
    "fmizonlib": "Zone G\u00e9n\u00e9rale",
    "fmizonnum": 14,
    "sortie": 7,
    "fmizonmax": 400,
    "entree": 35,
    "etablissement_etalib": "Piscine Grand Parc",
    "fmicourante": 28,
    "datemiseajour": "2025-02-18T07:30:00+00:00"
  },
  "2025-02-18T07:45:00+00:00": {
    "fmizonlib": "Zone G\u00e9n\u00e9rale",
    "fmizonnum": 14,
    "sortie": 21,
    "fmizonmax": 400,
    "entree": 35,
    "etablissement_etalib": "Piscine Grand Parc",
    "fmicourante": 14,
    "datemiseajour": "2025-02-18T07:45:00+00:00"
  },
  "2025-02-18T08:05:00+00:00": {
    "fmizonlib": "Zone G\u00e9n\u00e9rale",
    "fmizonnum": 14,
    "sortie": 34,
    "fmizonmax": 400,
    "entree": 87,
    "etablissement_etalib": "Piscine Grand Parc",
    "fmicourante": 53,
    "datemiseajour": "2025-02-18T08:05:00+00:00"
  },
  "2025-02-18T08:30:00+00:00": {
    "fmizonlib": "Zone G\u00e9n\u00e9rale",
    "fmizonnum": 14,
    "sortie": 35,
    "fmizonmax": 400,
    "entree": 87,
    "etablissement_etalib": "Piscine Grand Parc",
    "fmicourante": 52,
    "datemiseajour": "2025-02-18T08:30:00+00:00"
  },
  "2025-02-18T09:10:00+00:00": {
    "fmizonlib": "Zone G\u00e9n\u00e9rale",
    "fmizonnum": 14,
    "sortie": 66,
    "fmizonmax": 400,
    "entree": 137,
    "etablissement_etalib": "Piscine Grand Parc",
    "fmicourante": 71,
    "datemiseajour": "2025-02-18T09:10:00+00:00"
  },
  "2025-02-18T09:25:00+00:00": {
    "fmizonlib": "Zone G\u00e9n\u00e9rale",
    "fmizonnum": 14,
    "sortie": 85,
    "fmizonmax": 400,
    "entree": 137,
    "etablissement_etalib": "Piscine Grand Parc",
    "fmicourante": 52,
    "datemiseajour": "2025-02-18T09:25:00+00:00"
  },
  "2025-02-18T10:10:00+00:00": {
    "fmizonlib": "Zone G\u00e9n\u00e9rale",
    "fmizonnum": 14,
    "sortie": 135,
    "fmizonmax": 400,
    "entree": 204,
    "etablissement_etalib": "Piscine Grand Parc",
    "fmicourante": 69,
    "datemiseajour": "2025-02-18T10:10:00+00:00"
  },
  "2025-02-18T10:30:00+00:00": {
    "fmizonlib": "Zone G\u00e9n\u00e9rale",
    "fmizonnum": 14,
    "sortie": 137,
    "fmizonmax": 400,
    "entree": 204,
    "etablissement_etalib": "Piscine Grand Parc",
    "fmicourante": 67,
    "datemiseajour": "2025-02-18T10:30:00+00:00"
  },
  "2025-02-18T11:05:00+00:00": {
    "fmizonlib": "Zone G\u00e9n\u00e9rale",
    "fmizonnum": 14,
    "sortie": 139,
    "fmizonmax": 400,
    "entree": 237,
    "etablissement_etalib": "Piscine Grand Parc",
    "fmicourante": 98,
    "datemiseajour": "2025-02-18T11:05:00+00:00"
  },
  "2025-02-18T11:15:00+00:00": {
    "fmizonlib": "Zone G\u00e9n\u00e9rale",
    "fmizonnum": 14,
    "sortie": 161,
    "fmizonmax": 400,
    "entree": 257,
    "etablissement_etalib": "Piscine Grand Parc",
    "fmicourante": 96,
    "datemiseajour": "2025-02-18T11:15:00+00:00"
  },
  "2025-02-18T11:30:00+00:00": {
    "fmizonlib": "Zone G\u00e9n\u00e9rale",
    "fmizonnum": 14,
    "sortie": 182,
    "fmizonmax": 400,
    "entree": 278,
    "etablissement_etalib": "Piscine Grand Parc",
    "fmicourante": 96,
    "datemiseajour": "2025-02-18T11:30:00+00:00"
  },
  "2025-02-18T11:45:00+00:00": {
    "fmizonlib": "Zone G\u00e9n\u00e9rale",
    "fmizonnum": 14,
    "sortie": 186,
    "fmizonmax": 400,
    "entree": 290,
    "etablissement_etalib": "Piscine Grand Parc",
    "fmicourante": 104,
    "datemiseajour": "2025-02-18T11:45:00+00:00"
  },
  "2025-02-18T12:20:00+00:00": {
    "fmizonlib": "Zone G\u00e9n\u00e9rale",
    "fmizonnum": 14,
    "sortie": 224,
    "fmizonmax": 400,
    "entree": 299,
    "etablissement_etalib": "Piscine Grand Parc",
    "fmicourante": 75,
    "datemiseajour": "2025-02-18T12:20:00+00:00"
  },
  "2025-02-18T12:50:00+00:00": {
    "fmizonlib": "Zone G\u00e9n\u00e9rale",
    "fmizonnum": 14,
    "sortie": 259,
    "fmizonmax": 400,
    "entree": 299,
    "etablissement_etalib": "Piscine Grand Parc",
    "fmicourante": 40,
    "datemiseajour": "2025-02-18T12:50:00+00:00"
  },
  "2025-02-18T13:10:00+00:00": {
    "fmizonlib": "Zone G\u00e9n\u00e9rale",
    "fmizonnum": 14,
    "sortie": 304,
    "fmizonmax": 400,
    "entree": 367,
    "etablissement_etalib": "Piscine Grand Parc",
    "fmicourante": 63,
    "datemiseajour": "2025-02-18T13:10:00+00:00"
  },
  "2025-02-18T14:10:00+00:00": {
    "fmizonlib": "Zone G\u00e9n\u00e9rale",
    "fmizonnum": 14,
    "sortie": 371,
    "fmizonmax": 400,
    "entree": 429,
    "etablissement_etalib": "Piscine Grand Parc",
    "fmicourante": 58,
    "datemiseajour": "2025-02-18T14:10:00+00:00"
  },
  "2025-02-18T14:45:00+00:00": {
    "fmizonlib": "Zone G\u00e9n\u00e9rale",
    "fmizonnum": 14,
    "sortie": 371,
    "fmizonmax": 400,
    "entree": 446,
    "etablissement_etalib": "Piscine Grand Parc",
    "fmicourante": 75,
    "datemiseajour": "2025-02-18T14:45:00+00:00"
  },
  "2025-02-18T15:10:00+00:00": {
    "fmizonlib": "Zone G\u00e9n\u00e9rale",
    "fmizonnum": 14,
    "sortie": 436,
    "fmizonmax": 400,
    "entree": 456,
    "etablissement_etalib": "Piscine Grand Parc",
    "fmicourante": 20,
    "datemiseajour": "2025-02-18T15:10:00+00:00"
  },
  "2025-02-18T16:10:00+00:00": {
    "fmizonlib": "Zone G\u00e9n\u00e9rale",
    "fmizonnum": 14,
    "sortie": 437,
    "fmizonmax": 400,
    "entree": 480,
    "etablissement_etalib": "Piscine Grand Parc",
    "fmicourante": 43,
    "datemiseajour": "2025-02-18T16:10:00+00:00"
  },
  "2025-02-18T16:35:00+00:00": {
    "fmizonlib": "Zone G\u00e9n\u00e9rale",
    "fmizonnum": 14,
    "sortie": 439,
    "fmizonmax": 400,
    "entree": 507,
    "etablissement_etalib": "Piscine Grand Parc",
    "fmicourante": 68,
    "datemiseajour": "2025-02-18T16:35:00+00:00"
  },
  "2025-02-18T16:50:00+00:00": {
    "fmizonlib": "Zone G\u00e9n\u00e9rale",
    "fmizonnum": 14,
    "sortie": 455,
    "fmizonmax": 400,
    "entree": 516,
    "etablissement_etalib": "Piscine Grand Parc",
    "fmicourante": 61,
    "datemiseajour": "2025-02-18T16:50:00+00:00"
  },
  "2025-02-18T17:10:00+00:00": {
    "fmizonlib": "Zone G\u00e9n\u00e9rale",
    "fmizonnum": 14,
    "sortie": 464,
    "fmizonmax": 400,
    "entree": 549,
    "etablissement_etalib": "Piscine Grand Parc",
    "fmicourante": 85,
    "datemiseajour": "2025-02-18T17:10:00+00:00"
  },
  "2025-02-18T17:25:00+00:00": {
    "fmizonlib": "Zone G\u00e9n\u00e9rale",
    "fmizonnum": 14,
    "sortie": 476,
    "fmizonmax": 400,
    "entree": 571,
    "etablissement_etalib": "Piscine Grand Parc",
    "fmicourante": 95,
    "datemiseajour": "2025-02-18T17:25:00+00:00"
  },
  "2025-02-18T17:35:00+00:00": {
    "fmizonlib": "Zone G\u00e9n\u00e9rale",
    "fmizonnum": 14,
    "sortie": 484,
    "fmizonmax": 400,
    "entree": 600,
    "etablissement_etalib": "Piscine Grand Parc",
    "fmicourante": 116,
    "datemiseajour": "2025-02-18T17:35:00+00:00"
  },
  "2025-02-18T17:45:00+00:00": {
    "fmizonlib": "Zone G\u00e9n\u00e9rale",
    "fmizonnum": 14,
    "sortie": 494,
    "fmizonmax": 400,
    "entree": 626,
    "etablissement_etalib": "Piscine Grand Parc",
    "fmicourante": 132,
    "datemiseajour": "2025-02-18T17:45:00+00:00"
  },
  "2025-02-18T18:15:00+00:00": {
    "fmizonlib": "Zone G\u00e9n\u00e9rale",
    "fmizonnum": 14,
    "sortie": 522,
    "fmizonmax": 400,
    "entree": 669,
    "etablissement_etalib": "Piscine Grand Parc",
    "fmicourante": 147,
    "datemiseajour": "2025-02-18T18:15:00+00:00"
  },
  "2025-02-18T18:35:00+00:00": {
    "fmizonlib": "Zone G\u00e9n\u00e9rale",
    "fmizonnum": 14,
    "sortie": 552,
    "fmizonmax": 400,
    "entree": 685,
    "etablissement_etalib": "Piscine Grand Parc",
    "fmicourante": 133,
    "datemiseajour": "2025-02-18T18:35:00+00:00"
  },
  "2025-02-18T18:50:00+00:00": {
    "fmizonlib": "Zone G\u00e9n\u00e9rale",
    "fmizonnum": 14,
    "sortie": 584,
    "fmizonmax": 400,
    "entree": 691,
    "etablissement_etalib": "Piscine Grand Parc",
    "fmicourante": 107,
    "datemiseajour": "2025-02-18T18:50:00+00:00"
  },
  "2025-02-18T19:05:00+00:00": {
    "fmizonlib": "Zone G\u00e9n\u00e9rale",
    "fmizonnum": 14,
    "sortie": 614,
    "fmizonmax": 400,
    "entree": 700,
    "etablissement_etalib": "Piscine Grand Parc",
    "fmicourante": 86,
    "datemiseajour": "2025-02-18T19:05:00+00:00"
  },
  "2025-02-18T19:15:00+00:00": {
    "fmizonlib": "Zone G\u00e9n\u00e9rale",
    "fmizonnum": 14,
    "sortie": 624,
    "fmizonmax": 400,
    "entree": 701,
    "etablissement_etalib": "Piscine Grand Parc",
    "fmicourante": 77,
    "datemiseajour": "2025-02-18T19:15:00+00:00"
  },
  "2025-02-18T19:30:00+00:00": {
    "fmizonlib": "Zone G\u00e9n\u00e9rale",
    "fmizonnum": 14,
    "sortie": 639,
    "fmizonmax": 400,
    "entree": 707,
    "etablissement_etalib": "Piscine Grand Parc",
    "fmicourante": 68,
    "datemiseajour": "2025-02-18T19:30:00+00:00"
  },
  "2025-02-18T19:45:00+00:00": {
    "fmizonlib": "Zone G\u00e9n\u00e9rale",
    "fmizonnum": 14,
    "sortie": 656,
    "fmizonmax": 400,
    "entree": 736,
    "etablissement_etalib": "Piscine Grand Parc",
    "fmicourante": 80,
    "datemiseajour": "2025-02-18T19:45:00+00:00"
  },
  "2025-02-18T20:10:00+00:00": {
    "fmizonlib": "Zone G\u00e9n\u00e9rale",
    "fmizonnum": 14,
    "sortie": 694,
    "fmizonmax": 400,
    "entree": 742,
    "etablissement_etalib": "Piscine Grand Parc",
    "fmicourante": 48,
    "datemiseajour": "2025-02-18T20:10:00+00:00"
  },
  "2025-02-18T20:35:00+00:00": {
    "fmizonlib": "Zone G\u00e9n\u00e9rale",
    "fmizonnum": 14,
    "sortie": 694,
    "fmizonmax": 400,
    "entree": 743,
    "etablissement_etalib": "Piscine Grand Parc",
    "fmicourante": 49,
    "datemiseajour": "2025-02-18T20:35:00+00:00"
  }
}