{
  "2025-02-26T00:50:00+00:00": {
    "fmizonlib": "Zone G\u00e9n\u00e9rale",
    "fmizonnum": 14,
    "sortie": 0,
    "fmizonmax": 400,
    "entree": 0,
    "etablissement_etalib": "Piscine Grand Parc",
    "fmicourante": 0,
    "datemiseajour": "2025-02-26T00:50:00+00:00"
  },
  "2025-02-26T09:10:00+00:00": {
    "fmizonlib": "Zone G\u00e9n\u00e9rale",
    "fmizonnum": 14,
    "sortie": 0,
    "fmizonmax": 400,
    "entree": 42,
    "etablissement_etalib": "Piscine Grand Parc",
    "fmicourante": 42,
    "datemiseajour": "2025-02-26T09:10:00+00:00"
  },
  "2025-02-26T09:25:00+00:00": {
    "fmizonlib": "Zone G\u00e9n\u00e9rale",
    "fmizonnum": 14,
    "sortie": 0,
    "fmizonmax": 400,
    "entree": 77,
    "etablissement_etalib": "Piscine Grand Parc",
    "fmicourante": 77,
    "datemiseajour": "2025-02-26T09:25:00+00:00"
  },
  "2025-02-26T09:35:00+00:00": {
    "fmizonlib": "Zone G\u00e9n\u00e9rale",
    "fmizonnum": 14,
    "sortie": 0,
    "fmizonmax": 400,
    "entree": 84,
    "etablissement_etalib": "Piscine Grand Parc",
    "fmicourante": 84,
    "datemiseajour": "2025-02-26T09:35:00+00:00"
  },
  "2025-02-26T09:45:00+00:00": {
    "fmizonlib": "Zone G\u00e9n\u00e9rale",
    "fmizonnum": 14,
    "sortie": 1,
    "fmizonmax": 400,
    "entree": 95,
    "etablissement_etalib": "Piscine Grand Parc",
    "fmicourante": 94,
    "datemiseajour": "2025-02-26T09:45:00+00:00"
  },
  "2025-02-26T10:10:00+00:00": {
    "fmizonlib": "Zone G\u00e9n\u00e9rale",
    "fmizonnum": 14,
    "sortie": 11,
    "fmizonmax": 400,
    "entree": 110,
    "etablissement_etalib": "Piscine Grand Parc",
    "fmicourante": 99,
    "datemiseajour": "2025-02-26T10:10:00+00:00"
  },
  "2025-02-26T10:30:00+00:00": {
    "fmizonlib": "Zone G\u00e9n\u00e9rale",
    "fmizonnum": 14,
    "sortie": 34,
    "fmizonmax": 400,
    "entree": 122,
    "etablissement_etalib": "Piscine Grand Parc",
    "fmicourante": 88,
    "datemiseajour": "2025-02-26T10:30:00+00:00"
  },
  "2025-02-26T10:45:00+00:00": {
    "fmizonlib": "Zone G\u00e9n\u00e9rale",
    "fmizonnum": 14,
    "sortie": 54,
    "fmizonmax": 400,
    "entree": 142,
    "etablissement_etalib": "Piscine Grand Parc",
    "fmicourante": 88,
    "datemiseajour": "2025-02-26T10:45:00+00:00"
  },
  "2025-02-26T11:00:00+00:00": {
    "fmizonlib": "Zone G\u00e9n\u00e9rale",
    "fmizonnum": 14,
    "sortie": 77,
    "fmizonmax": 400,
    "entree": 150,
    "etablissement_etalib": "Piscine Grand Parc",
    "fmicourante": 73,
    "datemiseajour": "2025-02-26T11:00:00+00:00"
  },
  "2025-02-26T11:20:00+00:00": {
    "fmizonlib": "Zone G\u00e9n\u00e9rale",
    "fmizonnum": 14,
    "sortie": 103,
    "fmizonmax": 400,
    "entree": 170,
    "etablissement_etalib": "Piscine Grand Parc",
    "fmicourante": 67,
    "datemiseajour": "2025-02-26T11:20:00+00:00"
  }
}