{
  "2024-11-20T00:55:00+00:00": {
    "fmizonlib": "Zone Bassins",
    "fmizonnum": 12,
    "sortie": 0,
    "fmizonmax": 400,
    "entree": 0,
    "etablissement_etalib": "Piscine Galin",
    "fmicourante": 0,
    "datemiseajour": "2024-11-20T00:55:00+00:00"
  },
  "2024-11-20T07:10:00+00:00": {
    "fmizonlib": "Zone Bassins",
    "fmizonnum": 12,
    "sortie": 0,
    "fmizonmax": 400,
    "entree": 31,
    "etablissement_etalib": "Piscine Galin",
    "fmicourante": 31,
    "datemiseajour": "2024-11-20T07:10:00+00:00"
  },
  "2024-11-20T08:15:00+00:00": {
    "fmizonlib": "Zone Bassins",
    "fmizonnum": 12,
    "sortie": 0,
    "fmizonmax": 400,
    "entree": 36,
    "etablissement_etalib": "Piscine Galin",
    "fmicourante": 36,
    "datemiseajour": "2024-11-20T08:15:00+00:00"
  },
  "2024-11-20T08:40:00+00:00": {
    "fmizonlib": "Zone Bassins",
    "fmizonnum": 12,
    "sortie": 15,
    "fmizonmax": 400,
    "entree": 36,
    "etablissement_etalib": "Piscine Galin",
    "fmicourante": 21,
    "datemiseajour": "2024-11-20T08:40:00+00:00"
  },
  "2024-11-20T08:50:00+00:00": {
    "fmizonlib": "Zone Bassins",
    "fmizonnum": 12,
    "sortie": 37,
    "fmizonmax": 400,
    "entree": 36,
    "etablissement_etalib": "Piscine Galin",
    "fmicourante": -1,
    "datemiseajour": "2024-11-20T08:50:00+00:00"
  },
  "2024-11-20T09:10:00+00:00": {
    "fmizonlib": "Zone Bassins",
    "fmizonnum": 12,
    "sortie": 37,
    "fmizonmax": 400,
    "entree": 78,
    "etablissement_etalib": "Piscine Galin",
    "fmicourante": 41,
    "datemiseajour": "2024-11-20T09:10:00+00:00"
  },
  "2024-11-20T09:25:00+00:00": {
    "fmizonlib": "Zone Bassins",
    "fmizonnum": 12,
    "sortie": 41,
    "fmizonmax": 400,
    "entree": 87,
    "etablissement_etalib": "Piscine Galin",
    "fmicourante": 46,
    "datemiseajour": "2024-11-20T09:25:00+00:00"
  },
  "2024-11-20T09:35:00+00:00": {
    "fmizonlib": "Zone Bassins",
    "fmizonnum": 12,
    "sortie": 41,
    "fmizonmax": 400,
    "entree": 95,
    "etablissement_etalib": "Piscine Galin",
    "fmicourante": 54,
    "datemiseajour": "2024-11-20T09:35:00+00:00"
  },
  "2024-11-20T09:45:00+00:00": {
    "fmizonlib": "Zone Bassins",
    "fmizonnum": 12,
    "sortie": 41,
    "fmizonmax": 400,
    "entree": 103,
    "etablissement_etalib": "Piscine Galin",
    "fmicourante": 62,
    "datemiseajour": "2024-11-20T09:45:00+00:00"
  },
  "2024-11-20T10:05:00+00:00": {
    "fmizonlib": "Zone Bassins",
    "fmizonnum": 12,
    "sortie": 48,
    "fmizonmax": 400,
    "entree": 131,
    "etablissement_etalib": "Piscine Galin",
    "fmicourante": 83,
    "datemiseajour": "2024-11-20T10:05:00+00:00"
  },
  "2024-11-20T10:25:00+00:00": {
    "fmizonlib": "Zone Bassins",
    "fmizonnum": 12,
    "sortie": 57,
    "fmizonmax": 400,
    "entree": 138,
    "etablissement_etalib": "Piscine Galin",
    "fmicourante": 81,
    "datemiseajour": "2024-11-20T10:25:00+00:00"
  },
  "2024-11-20T10:45:00+00:00": {
    "fmizonlib": "Zone Bassins",
    "fmizonnum": 12,
    "sortie": 88,
    "fmizonmax": 400,
    "entree": 159,
    "etablissement_etalib": "Piscine Galin",
    "fmicourante": 71,
    "datemiseajour": "2024-11-20T10:45:00+00:00"
  },
  "2024-11-20T11:05:00+00:00": {
    "fmizonlib": "Zone Bassins",
    "fmizonnum": 12,
    "sortie": 123,
    "fmizonmax": 400,
    "entree": 167,
    "etablissement_etalib": "Piscine Galin",
    "fmicourante": 44,
    "datemiseajour": "2024-11-20T11:05:00+00:00"
  },
  "2024-11-20T11:20:00+00:00": {
    "fmizonlib": "Zone Bassins",
    "fmizonnum": 12,
    "sortie": 140,
    "fmizonmax": 400,
    "entree": 186,
    "etablissement_etalib": "Piscine Galin",
    "fmicourante": 46,
    "datemiseajour": "2024-11-20T11:20:00+00:00"
  },
  "2024-11-20T11:30:00+00:00": {
    "fmizonlib": "Zone Bassins",
    "fmizonnum": 12,
    "sortie": 144,
    "fmizonmax": 400,
    "entree": 201,
    "etablissement_etalib": "Piscine Galin",
    "fmicourante": 57,
    "datemiseajour": "2024-11-20T11:30:00+00:00"
  },
  "2024-11-20T11:40:00+00:00": {
    "fmizonlib": "Zone Bassins",
    "fmizonnum": 12,
    "sortie": 145,
    "fmizonmax": 400,
    "entree": 208,
    "etablissement_etalib": "Piscine Galin",
    "fmicourante": 63,
    "datemiseajour": "2024-11-20T11:40:00+00:00"
  },
  "2024-11-20T12:20:00+00:00": {
    "fmizonlib": "Zone Bassins",
    "fmizonnum": 12,
    "sortie": 178,
    "fmizonmax": 400,
    "entree": 219,
    "etablissement_etalib": "Piscine Galin",
    "fmicourante": 41,
    "datemiseajour": "2024-11-20T12:20:00+00:00"
  },
  "2024-11-20T12:55:00+00:00": {
    "fmizonlib": "Zone Bassins",
    "fmizonnum": 12,
    "sortie": 219,
    "fmizonmax": 400,
    "entree": 254,
    "etablissement_etalib": "Piscine Galin",
    "fmicourante": 35,
    "datemiseajour": "2024-11-20T12:55:00+00:00"
  },
  "2024-11-20T13:25:00+00:00": {
    "fmizonlib": "Zone Bassins",
    "fmizonnum": 12,
    "sortie": 219,
    "fmizonmax": 400,
    "entree": 261,
    "etablissement_etalib": "Piscine Galin",
    "fmicourante": 42,
    "datemiseajour": "2024-11-20T13:25:00+00:00"
  }
}