{
  "2023-10-09T00:35:00+00:00": {
    "fmizonlib": "Zone G\u00e9n\u00e9rale",
    "fmizonnum": 9,
    "sortie": 0,
    "fmizonmax": 342,
    "entree": 0,
    "etablissement_etalib": "Piscine Tissot",
    "fmicourante": 0,
    "datemiseajour": "2023-10-09T00:35:00+00:00"
  },
  "2023-10-09T10:25:00+00:00": {
    "fmizonlib": "Zone G\u00e9n\u00e9rale",
    "fmizonnum": 9,
    "sortie": 0,
    "fmizonmax": 342,
    "entree": 64,
    "etablissement_etalib": "Piscine Tissot",
    "fmicourante": 64,
    "datemiseajour": "2023-10-09T10:25:00+00:00"
  },
  "2023-10-09T10:35:00+00:00": {
    "fmizonlib": "Zone G\u00e9n\u00e9rale",
    "fmizonnum": 9,
    "sortie": 0,
    "fmizonmax": 342,
    "entree": 72,
    "etablissement_etalib": "Piscine Tissot",
    "fmicourante": 72,
    "datemiseajour": "2023-10-09T10:35:00+00:00"
  },
  "2023-10-09T10:45:00+00:00": {
    "fmizonlib": "Zone G\u00e9n\u00e9rale",
    "fmizonnum": 9,
    "sortie": 1,
    "fmizonmax": 342,
    "entree": 80,
    "etablissement_etalib": "Piscine Tissot",
    "fmicourante": 79,
    "datemiseajour": "2023-10-09T10:45:00+00:00"
  },
  "2023-10-09T11:00:00+00:00": {
    "fmizonlib": "Zone G\u00e9n\u00e9rale",
    "fmizonnum": 9,
    "sortie": 13,
    "fmizonmax": 342,
    "entree": 87,
    "etablissement_etalib": "Piscine Tissot",
    "fmicourante": 74,
    "datemiseajour": "2023-10-09T11:00:00+00:00"
  },
  "2023-10-09T11:10:00+00:00": {
    "fmizonlib": "Zone G\u00e9n\u00e9rale",
    "fmizonnum": 9,
    "sortie": 21,
    "fmizonmax": 342,
    "entree": 89,
    "etablissement_etalib": "Piscine Tissot",
    "fmicourante": 68,
    "datemiseajour": "2023-10-09T11:10:00+00:00"
  },
  "2023-10-09T11:30:00+00:00": {
    "fmizonlib": "Zone G\u00e9n\u00e9rale",
    "fmizonnum": 9,
    "sortie": 52,
    "fmizonmax": 342,
    "entree": 89,
    "etablissement_etalib": "Piscine Tissot",
    "fmicourante": 37,
    "datemiseajour": "2023-10-09T11:30:00+00:00"
  },
  "2023-10-09T11:45:00+00:00": {
    "fmizonlib": "Zone G\u00e9n\u00e9rale",
    "fmizonnum": 9,
    "sortie": 65,
    "fmizonmax": 342,
    "entree": 89,
    "etablissement_etalib": "Piscine Tissot",
    "fmicourante": 24,
    "datemiseajour": "2023-10-09T11:45:00+00:00"
  },
  "2023-10-09T12:15:00+00:00": {
    "fmizonlib": "Zone G\u00e9n\u00e9rale",
    "fmizonnum": 9,
    "sortie": 87,
    "fmizonmax": 342,
    "entree": 89,
    "etablissement_etalib": "Piscine Tissot",
    "fmicourante": 2,
    "datemiseajour": "2023-10-09T12:15:00+00:00"
  },
  "2023-10-09T14:05:00+00:00": {
    "fmizonlib": "Zone G\u00e9n\u00e9rale",
    "fmizonnum": 9,
    "sortie": 105,
    "fmizonmax": 342,
    "entree": 119,
    "etablissement_etalib": "Piscine Tissot",
    "fmicourante": 14,
    "datemiseajour": "2023-10-09T14:05:00+00:00"
  },
  "2023-10-09T14:20:00+00:00": {
    "fmizonlib": "Zone G\u00e9n\u00e9rale",
    "fmizonnum": 9,
    "sortie": 105,
    "fmizonmax": 342,
    "entree": 129,
    "etablissement_etalib": "Piscine Tissot",
    "fmicourante": 24,
    "datemiseajour": "2023-10-09T14:20:00+00:00"
  },
  "2023-10-09T14:30:00+00:00": {
    "fmizonlib": "Zone G\u00e9n\u00e9rale",
    "fmizonnum": 9,
    "sortie": 105,
    "fmizonmax": 342,
    "entree": 134,
    "etablissement_etalib": "Piscine Tissot",
    "fmicourante": 29,
    "datemiseajour": "2023-10-09T14:30:00+00:00"
  },
  "2023-10-09T14:45:00+00:00": {
    "fmizonlib": "Zone G\u00e9n\u00e9rale",
    "fmizonnum": 9,
    "sortie": 105,
    "fmizonmax": 342,
    "entree": 139,
    "etablissement_etalib": "Piscine Tissot",
    "fmicourante": 34,
    "datemiseajour": "2023-10-09T14:45:00+00:00"
  },
  "2023-10-09T15:00:00+00:00": {
    "fmizonlib": "Zone G\u00e9n\u00e9rale",
    "fmizonnum": 9,
    "sortie": 111,
    "fmizonmax": 342,
    "entree": 166,
    "etablissement_etalib": "Piscine Tissot",
    "fmicourante": 55,
    "datemiseajour": "2023-10-09T15:00:00+00:00"
  },
  "2023-10-09T15:15:00+00:00": {
    "fmizonlib": "Zone G\u00e9n\u00e9rale",
    "fmizonnum": 9,
    "sortie": 132,
    "fmizonmax": 342,
    "entree": 174,
    "etablissement_etalib": "Piscine Tissot",
    "fmicourante": 42,
    "datemiseajour": "2023-10-09T15:15:00+00:00"
  },
  "2023-10-09T15:30:00+00:00": {
    "fmizonlib": "Zone G\u00e9n\u00e9rale",
    "fmizonnum": 9,
    "sortie": 136,
    "fmizonmax": 342,
    "entree": 186,
    "etablissement_etalib": "Piscine Tissot",
    "fmicourante": 50,
    "datemiseajour": "2023-10-09T15:30:00+00:00"
  },
  "2023-10-09T15:45:00+00:00": {
    "fmizonlib": "Zone G\u00e9n\u00e9rale",
    "fmizonnum": 9,
    "sortie": 148,
    "fmizonmax": 342,
    "entree": 203,
    "etablissement_etalib": "Piscine Tissot",
    "fmicourante": 55,
    "datemiseajour": "2023-10-09T15:45:00+00:00"
  }
}