{
  "2025-09-09T00:55:00+00:00": {
    "fmizonlib": "Zone Bassins",
    "fmizonnum": 12,
    "sortie": 0,
    "fmizonmax": 400,
    "entree": 0,
    "etablissement_etalib": "Piscine Galin",
    "fmicourante": 0,
    "datemiseajour": "2025-09-09T00:55:00+00:00"
  },
  "2025-09-09T07:45:00+00:00": {
    "fmizonlib": "Zone Bassins",
    "fmizonnum": 12,
    "sortie": 0,
    "fmizonmax": 400,
    "entree": 55,
    "etablissement_etalib": "Piscine Galin",
    "fmicourante": 55,
    "datemiseajour": "2025-09-09T07:45:00+00:00"
  },
  "2025-09-09T08:40:00+00:00": {
    "fmizonlib": "Zone Bassins",
    "fmizonnum": 12,
    "sortie": 0,
    "fmizonmax": 400,
    "entree": 93,
    "etablissement_etalib": "Piscine Galin",
    "fmicourante": 93,
    "datemiseajour": "2025-09-09T08:40:00+00:00"
  },
  "2025-09-09T08:50:00+00:00": {
    "fmizonlib": "Zone Bassins",
    "fmizonnum": 12,
    "sortie": 54,
    "fmizonmax": 400,
    "entree": 93,
    "etablissement_etalib": "Piscine Galin",
    "fmicourante": 39,
    "datemiseajour": "2025-09-09T08:50:00+00:00"
  },
  "2025-09-09T09:10:00+00:00": {
    "fmizonlib": "Zone Bassins",
    "fmizonnum": 12,
    "sortie": 54,
    "fmizonmax": 400,
    "entree": 100,
    "etablissement_etalib": "Piscine Galin",
    "fmicourante": 46,
    "datemiseajour": "2025-09-09T09:10:00+00:00"
  },
  "2025-09-09T09:30:00+00:00": {
    "fmizonlib": "Zone Bassins",
    "fmizonnum": 12,
    "sortie": 55,
    "fmizonmax": 400,
    "entree": 100,
    "etablissement_etalib": "Piscine Galin",
    "fmicourante": 45,
    "datemiseajour": "2025-09-09T09:30:00+00:00"
  },
  "2025-09-09T09:40:00+00:00": {
    "fmizonlib": "Zone Bassins",
    "fmizonnum": 12,
    "sortie": 87,
    "fmizonmax": 400,
    "entree": 100,
    "etablissement_etalib": "Piscine Galin",
    "fmicourante": 13,
    "datemiseajour": "2025-09-09T09:40:00+00:00"
  },
  "2025-09-09T10:10:00+00:00": {
    "fmizonlib": "Zone Bassins",
    "fmizonnum": 12,
    "sortie": 87,
    "fmizonmax": 400,
    "entree": 141,
    "etablissement_etalib": "Piscine Galin",
    "fmicourante": 54,
    "datemiseajour": "2025-09-09T10:10:00+00:00"
  },
  "2025-09-09T10:25:00+00:00": {
    "fmizonlib": "Zone Bassins",
    "fmizonnum": 12,
    "sortie": 94,
    "fmizonmax": 400,
    "entree": 161,
    "etablissement_etalib": "Piscine Galin",
    "fmicourante": 67,
    "datemiseajour": "2025-09-09T10:25:00+00:00"
  },
  "2025-09-09T10:45:00+00:00": {
    "fmizonlib": "Zone Bassins",
    "fmizonnum": 12,
    "sortie": 95,
    "fmizonmax": 400,
    "entree": 175,
    "etablissement_etalib": "Piscine Galin",
    "fmicourante": 80,
    "datemiseajour": "2025-09-09T10:45:00+00:00"
  },
  "2025-09-09T11:10:00+00:00": {
    "fmizonlib": "Zone Bassins",
    "fmizonnum": 12,
    "sortie": 125,
    "fmizonmax": 400,
    "entree": 191,
    "etablissement_etalib": "Piscine Galin",
    "fmicourante": 66,
    "datemiseajour": "2025-09-09T11:10:00+00:00"
  },
  "2025-09-09T11:20:00+00:00": {
    "fmizonlib": "Zone Bassins",
    "fmizonnum": 12,
    "sortie": 139,
    "fmizonmax": 400,
    "entree": 193,
    "etablissement_etalib": "Piscine Galin",
    "fmicourante": 54,
    "datemiseajour": "2025-09-09T11:20:00+00:00"
  },
  "2025-09-09T11:25:00+00:00": {
    "fmizonlib": "Zone Bassins",
    "fmizonnum": 12,
    "sortie": 147,
    "fmizonmax": 400,
    "entree": 193,
    "etablissement_etalib": "Piscine Galin",
    "fmicourante": 46,
    "datemiseajour": "2025-09-09T11:25:00+00:00"
  },
  "2025-09-09T11:45:00+00:00": {
    "fmizonlib": "Zone Bassins",
    "fmizonnum": 12,
    "sortie": 168,
    "fmizonmax": 400,
    "entree": 193,
    "etablissement_etalib": "Piscine Galin",
    "fmicourante": 25,
    "datemiseajour": "2025-09-09T11:45:00+00:00"
  },
  "2025-09-09T12:20:00+00:00": {
    "fmizonlib": "Zone Bassins",
    "fmizonnum": 12,
    "sortie": 185,
    "fmizonmax": 400,
    "entree": 193,
    "etablissement_etalib": "Piscine Galin",
    "fmicourante": 8,
    "datemiseajour": "2025-09-09T12:20:00+00:00"
  },
  "2025-09-09T13:05:00+00:00": {
    "fmizonlib": "Zone Bassins",
    "fmizonnum": 12,
    "sortie": 187,
    "fmizonmax": 400,
    "entree": 238,
    "etablissement_etalib": "Piscine Galin",
    "fmicourante": 51,
    "datemiseajour": "2025-09-09T13:05:00+00:00"
  },
  "2025-09-09T14:05:00+00:00": {
    "fmizonlib": "Zone Bassins",
    "fmizonnum": 12,
    "sortie": 189,
    "fmizonmax": 400,
    "entree": 241,
    "etablissement_etalib": "Piscine Galin",
    "fmicourante": 52,
    "datemiseajour": "2025-09-09T14:05:00+00:00"
  },
  "2025-09-09T15:10:00+00:00": {
    "fmizonlib": "Zone Bassins",
    "fmizonnum": 12,
    "sortie": 244,
    "fmizonmax": 400,
    "entree": 288,
    "etablissement_etalib": "Piscine Galin",
    "fmicourante": 44,
    "datemiseajour": "2025-09-09T15:10:00+00:00"
  },
  "2025-09-09T15:25:00+00:00": {
    "fmizonlib": "Zone Bassins",
    "fmizonnum": 12,
    "sortie": 244,
    "fmizonmax": 400,
    "entree": 296,
    "etablissement_etalib": "Piscine Galin",
    "fmicourante": 52,
    "datemiseajour": "2025-09-09T15:25:00+00:00"
  },
  "2025-09-09T15:45:00+00:00": {
    "fmizonlib": "Zone Bassins",
    "fmizonnum": 12,
    "sortie": 246,
    "fmizonmax": 400,
    "entree": 334,
    "etablissement_etalib": "Piscine Galin",
    "fmicourante": 88,
    "datemiseajour": "2025-09-09T15:45:00+00:00"
  }
}