{
  "2023-12-11T00:40:00+00:00": {
    "fmizonlib": "Zone Bassins",
    "fmizonnum": 12,
    "sortie": 0,
    "fmizonmax": 400,
    "entree": 0,
    "etablissement_etalib": "Piscine Galin",
    "fmicourante": 0,
    "datemiseajour": "2023-12-11T00:40:00+00:00"
  },
  "2023-12-11T07:05:00+00:00": {
    "fmizonlib": "Zone Bassins",
    "fmizonnum": 12,
    "sortie": 0,
    "fmizonmax": 400,
    "entree": 11,
    "etablissement_etalib": "Piscine Galin",
    "fmicourante": 11,
    "datemiseajour": "2023-12-11T07:05:00+00:00"
  },
  "2023-12-11T08:20:00+00:00": {
    "fmizonlib": "Zone Bassins",
    "fmizonnum": 12,
    "sortie": 13,
    "fmizonmax": 400,
    "entree": 11,
    "etablissement_etalib": "Piscine Galin",
    "fmicourante": -2,
    "datemiseajour": "2023-12-11T08:20:00+00:00"
  },
  "2023-12-11T09:15:00+00:00": {
    "fmizonlib": "Zone Bassins",
    "fmizonnum": 12,
    "sortie": 55,
    "fmizonmax": 400,
    "entree": 50,
    "etablissement_etalib": "Piscine Galin",
    "fmicourante": -5,
    "datemiseajour": "2023-12-11T09:15:00+00:00"
  },
  "2023-12-11T10:05:00+00:00": {
    "fmizonlib": "Zone Bassins",
    "fmizonnum": 12,
    "sortie": 94,
    "fmizonmax": 400,
    "entree": 63,
    "etablissement_etalib": "Piscine Galin",
    "fmicourante": -31,
    "datemiseajour": "2023-12-11T10:05:00+00:00"
  },
  "2023-12-11T11:05:00+00:00": {
    "fmizonlib": "Zone Bassins",
    "fmizonnum": 12,
    "sortie": 112,
    "fmizonmax": 400,
    "entree": 114,
    "etablissement_etalib": "Piscine Galin",
    "fmicourante": 2,
    "datemiseajour": "2023-12-11T11:05:00+00:00"
  },
  "2023-12-11T11:20:00+00:00": {
    "fmizonlib": "Zone Bassins",
    "fmizonnum": 12,
    "sortie": 113,
    "fmizonmax": 400,
    "entree": 131,
    "etablissement_etalib": "Piscine Galin",
    "fmicourante": 18,
    "datemiseajour": "2023-12-11T11:20:00+00:00"
  },
  "2023-12-11T11:25:00+00:00": {
    "fmizonlib": "Zone Bassins",
    "fmizonnum": 12,
    "sortie": 113,
    "fmizonmax": 400,
    "entree": 135,
    "etablissement_etalib": "Piscine Galin",
    "fmicourante": 22,
    "datemiseajour": "2023-12-11T11:25:00+00:00"
  },
  "2023-12-11T11:45:00+00:00": {
    "fmizonlib": "Zone Bassins",
    "fmizonnum": 12,
    "sortie": 113,
    "fmizonmax": 400,
    "entree": 146,
    "etablissement_etalib": "Piscine Galin",
    "fmicourante": 33,
    "datemiseajour": "2023-12-11T11:45:00+00:00"
  },
  "2023-12-11T12:10:00+00:00": {
    "fmizonlib": "Zone Bassins",
    "fmizonnum": 12,
    "sortie": 129,
    "fmizonmax": 400,
    "entree": 154,
    "etablissement_etalib": "Piscine Galin",
    "fmicourante": 25,
    "datemiseajour": "2023-12-11T12:10:00+00:00"
  },
  "2023-12-11T12:40:00+00:00": {
    "fmizonlib": "Zone Bassins",
    "fmizonnum": 12,
    "sortie": 154,
    "fmizonmax": 400,
    "entree": 154,
    "etablissement_etalib": "Piscine Galin",
    "fmicourante": 0,
    "datemiseajour": "2023-12-11T12:40:00+00:00"
  },
  "2023-12-11T13:10:00+00:00": {
    "fmizonlib": "Zone Bassins",
    "fmizonnum": 12,
    "sortie": 170,
    "fmizonmax": 400,
    "entree": 154,
    "etablissement_etalib": "Piscine Galin",
    "fmicourante": -16,
    "datemiseajour": "2023-12-11T13:10:00+00:00"
  },
  "2023-12-11T14:05:00+00:00": {
    "fmizonlib": "Zone Bassins",
    "fmizonnum": 12,
    "sortie": 206,
    "fmizonmax": 400,
    "entree": 198,
    "etablissement_etalib": "Piscine Galin",
    "fmicourante": -8,
    "datemiseajour": "2023-12-11T14:05:00+00:00"
  },
  "2023-12-11T14:20:00+00:00": {
    "fmizonlib": "Zone Bassins",
    "fmizonnum": 12,
    "sortie": 209,
    "fmizonmax": 400,
    "entree": 198,
    "etablissement_etalib": "Piscine Galin",
    "fmicourante": -11,
    "datemiseajour": "2023-12-11T14:20:00+00:00"
  },
  "2023-12-11T15:05:00+00:00": {
    "fmizonlib": "Zone Bassins",
    "fmizonnum": 12,
    "sortie": 231,
    "fmizonmax": 400,
    "entree": 209,
    "etablissement_etalib": "Piscine Galin",
    "fmicourante": -22,
    "datemiseajour": "2023-12-11T15:05:00+00:00"
  },
  "2023-12-11T15:20:00+00:00": {
    "fmizonlib": "Zone Bassins",
    "fmizonnum": 12,
    "sortie": 254,
    "fmizonmax": 400,
    "entree": 209,
    "etablissement_etalib": "Piscine Galin",
    "fmicourante": -45,
    "datemiseajour": "2023-12-11T15:20:00+00:00"
  }
}