{
  "2025-05-21T01:00:00+00:00": {
    "fmizonlib": "Zone G\u00e9n\u00e9rale",
    "fmizonnum": 14,
    "sortie": 0,
    "fmizonmax": 400,
    "entree": 0,
    "etablissement_etalib": "Piscine Grand Parc",
    "fmicourante": 0,
    "datemiseajour": "2025-05-21T01:00:00+00:00"
  },
  "2025-05-21T07:10:00+00:00": {
    "fmizonlib": "Zone G\u00e9n\u00e9rale",
    "fmizonnum": 14,
    "sortie": 0,
    "fmizonmax": 400,
    "entree": 8,
    "etablissement_etalib": "Piscine Grand Parc",
    "fmicourante": 8,
    "datemiseajour": "2025-05-21T07:10:00+00:00"
  },
  "2025-05-21T08:15:00+00:00": {
    "fmizonlib": "Zone G\u00e9n\u00e9rale",
    "fmizonnum": 14,
    "sortie": 4,
    "fmizonmax": 400,
    "entree": 67,
    "etablissement_etalib": "Piscine Grand Parc",
    "fmicourante": 63,
    "datemiseajour": "2025-05-21T08:15:00+00:00"
  },
  "2025-05-21T08:40:00+00:00": {
    "fmizonlib": "Zone G\u00e9n\u00e9rale",
    "fmizonnum": 14,
    "sortie": 50,
    "fmizonmax": 400,
    "entree": 88,
    "etablissement_etalib": "Piscine Grand Parc",
    "fmicourante": 38,
    "datemiseajour": "2025-05-21T08:40:00+00:00"
  },
  "2025-05-21T09:10:00+00:00": {
    "fmizonlib": "Zone G\u00e9n\u00e9rale",
    "fmizonnum": 14,
    "sortie": 58,
    "fmizonmax": 400,
    "entree": 149,
    "etablissement_etalib": "Piscine Grand Parc",
    "fmicourante": 91,
    "datemiseajour": "2025-05-21T09:10:00+00:00"
  },
  "2025-05-21T09:30:00+00:00": {
    "fmizonlib": "Zone G\u00e9n\u00e9rale",
    "fmizonnum": 14,
    "sortie": 94,
    "fmizonmax": 400,
    "entree": 169,
    "etablissement_etalib": "Piscine Grand Parc",
    "fmicourante": 75,
    "datemiseajour": "2025-05-21T09:30:00+00:00"
  },
  "2025-05-21T09:45:00+00:00": {
    "fmizonlib": "Zone G\u00e9n\u00e9rale",
    "fmizonnum": 14,
    "sortie": 110,
    "fmizonmax": 400,
    "entree": 182,
    "etablissement_etalib": "Piscine Grand Parc",
    "fmicourante": 72,
    "datemiseajour": "2025-05-21T09:45:00+00:00"
  },
  "2025-05-21T10:10:00+00:00": {
    "fmizonlib": "Zone G\u00e9n\u00e9rale",
    "fmizonnum": 14,
    "sortie": 155,
    "fmizonmax": 400,
    "entree": 192,
    "etablissement_etalib": "Piscine Grand Parc",
    "fmicourante": 37,
    "datemiseajour": "2025-05-21T10:10:00+00:00"
  },
  "2025-05-21T10:35:00+00:00": {
    "fmizonlib": "Zone G\u00e9n\u00e9rale",
    "fmizonnum": 14,
    "sortie": 187,
    "fmizonmax": 400,
    "entree": 239,
    "etablissement_etalib": "Piscine Grand Parc",
    "fmicourante": 52,
    "datemiseajour": "2025-05-21T10:35:00+00:00"
  }
}