{
  "2025-10-15T00:50:00+00:00": {
    "fmizonlib": "Zone G\u00e9n\u00e9rale",
    "fmizonnum": 14,
    "sortie": 0,
    "fmizonmax": 300,
    "entree": 0,
    "etablissement_etalib": "Piscine Grand Parc",
    "fmicourante": 0,
    "datemiseajour": "2025-10-15T00:50:00+00:00"
  },
  "2025-10-15T06:15:00+00:00": {
    "fmizonlib": "Zone G\u00e9n\u00e9rale",
    "fmizonnum": 14,
    "sortie": 0,
    "fmizonmax": 300,
    "entree": 27,
    "etablissement_etalib": "Piscine Grand Parc",
    "fmicourante": 27,
    "datemiseajour": "2025-10-15T06:15:00+00:00"
  },
  "2025-10-15T07:05:00+00:00": {
    "fmizonlib": "Zone G\u00e9n\u00e9rale",
    "fmizonnum": 14,
    "sortie": 0,
    "fmizonmax": 300,
    "entree": 90,
    "etablissement_etalib": "Piscine Grand Parc",
    "fmicourante": 90,
    "datemiseajour": "2025-10-15T07:05:00+00:00"
  },
  "2025-10-15T07:25:00+00:00": {
    "fmizonlib": "Zone G\u00e9n\u00e9rale",
    "fmizonnum": 14,
    "sortie": 27,
    "fmizonmax": 300,
    "entree": 96,
    "etablissement_etalib": "Piscine Grand Parc",
    "fmicourante": 69,
    "datemiseajour": "2025-10-15T07:25:00+00:00"
  },
  "2025-10-15T08:15:00+00:00": {
    "fmizonlib": "Zone G\u00e9n\u00e9rale",
    "fmizonnum": 14,
    "sortie": 32,
    "fmizonmax": 300,
    "entree": 156,
    "etablissement_etalib": "Piscine Grand Parc",
    "fmicourante": 124,
    "datemiseajour": "2025-10-15T08:15:00+00:00"
  },
  "2025-10-15T08:45:00+00:00": {
    "fmizonlib": "Zone G\u00e9n\u00e9rale",
    "fmizonnum": 14,
    "sortie": 99,
    "fmizonmax": 300,
    "entree": 179,
    "etablissement_etalib": "Piscine Grand Parc",
    "fmicourante": 80,
    "datemiseajour": "2025-10-15T08:45:00+00:00"
  },
  "2025-10-15T09:10:00+00:00": {
    "fmizonlib": "Zone G\u00e9n\u00e9rale",
    "fmizonnum": 14,
    "sortie": 117,
    "fmizonmax": 300,
    "entree": 203,
    "etablissement_etalib": "Piscine Grand Parc",
    "fmicourante": 86,
    "datemiseajour": "2025-10-15T09:10:00+00:00"
  },
  "2025-10-15T09:30:00+00:00": {
    "fmizonlib": "Zone G\u00e9n\u00e9rale",
    "fmizonnum": 14,
    "sortie": 156,
    "fmizonmax": 300,
    "entree": 218,
    "etablissement_etalib": "Piscine Grand Parc",
    "fmicourante": 62,
    "datemiseajour": "2025-10-15T09:30:00+00:00"
  },
  "2025-10-15T09:45:00+00:00": {
    "fmizonlib": "Zone G\u00e9n\u00e9rale",
    "fmizonnum": 14,
    "sortie": 162,
    "fmizonmax": 300,
    "entree": 230,
    "etablissement_etalib": "Piscine Grand Parc",
    "fmicourante": 68,
    "datemiseajour": "2025-10-15T09:45:00+00:00"
  },
  "2025-10-15T10:05:00+00:00": {
    "fmizonlib": "Zone G\u00e9n\u00e9rale",
    "fmizonnum": 14,
    "sortie": 186,
    "fmizonmax": 300,
    "entree": 251,
    "etablissement_etalib": "Piscine Grand Parc",
    "fmicourante": 65,
    "datemiseajour": "2025-10-15T10:05:00+00:00"
  },
  "2025-10-15T10:35:00+00:00": {
    "fmizonlib": "Zone G\u00e9n\u00e9rale",
    "fmizonnum": 14,
    "sortie": 218,
    "fmizonmax": 300,
    "entree": 278,
    "etablissement_etalib": "Piscine Grand Parc",
    "fmicourante": 60,
    "datemiseajour": "2025-10-15T10:35:00+00:00"
  },
  "2025-10-15T10:50:00+00:00": {
    "fmizonlib": "Zone G\u00e9n\u00e9rale",
    "fmizonnum": 14,
    "sortie": 228,
    "fmizonmax": 300,
    "entree": 296,
    "etablissement_etalib": "Piscine Grand Parc",
    "fmicourante": 68,
    "datemiseajour": "2025-10-15T10:50:00+00:00"
  },
  "2025-10-15T11:10:00+00:00": {
    "fmizonlib": "Zone G\u00e9n\u00e9rale",
    "fmizonnum": 14,
    "sortie": 246,
    "fmizonmax": 300,
    "entree": 298,
    "etablissement_etalib": "Piscine Grand Parc",
    "fmicourante": 52,
    "datemiseajour": "2025-10-15T11:10:00+00:00"
  },
  "2025-10-15T11:25:00+00:00": {
    "fmizonlib": "Zone G\u00e9n\u00e9rale",
    "fmizonnum": 14,
    "sortie": 262,
    "fmizonmax": 300,
    "entree": 323,
    "etablissement_etalib": "Piscine Grand Parc",
    "fmicourante": 61,
    "datemiseajour": "2025-10-15T11:25:00+00:00"
  },
  "2025-10-15T11:30:00+00:00": {
    "fmizonlib": "Zone G\u00e9n\u00e9rale",
    "fmizonnum": 14,
    "sortie": 264,
    "fmizonmax": 300,
    "entree": 331,
    "etablissement_etalib": "Piscine Grand Parc",
    "fmicourante": 67,
    "datemiseajour": "2025-10-15T11:30:00+00:00"
  },
  "2025-10-15T11:45:00+00:00": {
    "fmizonlib": "Zone G\u00e9n\u00e9rale",
    "fmizonnum": 14,
    "sortie": 294,
    "fmizonmax": 300,
    "entree": 344,
    "etablissement_etalib": "Piscine Grand Parc",
    "fmicourante": 50,
    "datemiseajour": "2025-10-15T11:45:00+00:00"
  },
  "2025-10-15T12:25:00+00:00": {
    "fmizonlib": "Zone G\u00e9n\u00e9rale",
    "fmizonnum": 14,
    "sortie": 303,
    "fmizonmax": 300,
    "entree": 345,
    "etablissement_etalib": "Piscine Grand Parc",
    "fmicourante": 42,
    "datemiseajour": "2025-10-15T12:25:00+00:00"
  },
  "2025-10-15T13:00:00+00:00": {
    "fmizonlib": "Zone G\u00e9n\u00e9rale",
    "fmizonnum": 14,
    "sortie": 309,
    "fmizonmax": 300,
    "entree": 351,
    "etablissement_etalib": "Piscine Grand Parc",
    "fmicourante": 42,
    "datemiseajour": "2025-10-15T13:00:00+00:00"
  },
  "2025-10-15T13:40:00+00:00": {
    "fmizonlib": "Zone G\u00e9n\u00e9rale",
    "fmizonnum": 14,
    "sortie": 351,
    "fmizonmax": 300,
    "entree": 417,
    "etablissement_etalib": "Piscine Grand Parc",
    "fmicourante": 66,
    "datemiseajour": "2025-10-15T13:40:00+00:00"
  },
  "2025-10-15T13:50:00+00:00": {
    "fmizonlib": "Zone G\u00e9n\u00e9rale",
    "fmizonnum": 14,
    "sortie": 355,
    "fmizonmax": 300,
    "entree": 425,
    "etablissement_etalib": "Piscine Grand Parc",
    "fmicourante": 70,
    "datemiseajour": "2025-10-15T13:50:00+00:00"
  },
  "2025-10-15T14:10:00+00:00": {
    "fmizonlib": "Zone G\u00e9n\u00e9rale",
    "fmizonnum": 14,
    "sortie": 365,
    "fmizonmax": 300,
    "entree": 443,
    "etablissement_etalib": "Piscine Grand Parc",
    "fmicourante": 78,
    "datemiseajour": "2025-10-15T14:10:00+00:00"
  },
  "2025-10-15T14:30:00+00:00": {
    "fmizonlib": "Zone G\u00e9n\u00e9rale",
    "fmizonnum": 14,
    "sortie": 382,
    "fmizonmax": 300,
    "entree": 457,
    "etablissement_etalib": "Piscine Grand Parc",
    "fmicourante": 75,
    "datemiseajour": "2025-10-15T14:30:00+00:00"
  },
  "2025-10-15T14:50:00+00:00": {
    "fmizonlib": "Zone G\u00e9n\u00e9rale",
    "fmizonnum": 14,
    "sortie": 407,
    "fmizonmax": 300,
    "entree": 477,
    "etablissement_etalib": "Piscine Grand Parc",
    "fmicourante": 70,
    "datemiseajour": "2025-10-15T14:50:00+00:00"
  },
  "2025-10-15T15:10:00+00:00": {
    "fmizonlib": "Zone G\u00e9n\u00e9rale",
    "fmizonnum": 14,
    "sortie": 425,
    "fmizonmax": 300,
    "entree": 493,
    "etablissement_etalib": "Piscine Grand Parc",
    "fmicourante": 68,
    "datemiseajour": "2025-10-15T15:10:00+00:00"
  },
  "2025-10-15T15:20:00+00:00": {
    "fmizonlib": "Zone G\u00e9n\u00e9rale",
    "fmizonnum": 14,
    "sortie": 441,
    "fmizonmax": 300,
    "entree": 493,
    "etablissement_etalib": "Piscine Grand Parc",
    "fmicourante": 52,
    "datemiseajour": "2025-10-15T15:20:00+00:00"
  },
  "2025-10-15T15:40:00+00:00": {
    "fmizonlib": "Zone G\u00e9n\u00e9rale",
    "fmizonnum": 14,
    "sortie": 460,
    "fmizonmax": 300,
    "entree": 549,
    "etablissement_etalib": "Piscine Grand Parc",
    "fmicourante": 89,
    "datemiseajour": "2025-10-15T15:40:00+00:00"
  },
  "2025-10-15T15:45:00+00:00": {
    "fmizonlib": "Zone G\u00e9n\u00e9rale",
    "fmizonnum": 14,
    "sortie": 462,
    "fmizonmax": 300,
    "entree": 561,
    "etablissement_etalib": "Piscine Grand Parc",
    "fmicourante": 99,
    "datemiseajour": "2025-10-15T15:45:00+00:00"
  },
  "2025-10-15T16:05:00+00:00": {
    "fmizonlib": "Zone G\u00e9n\u00e9rale",
    "fmizonnum": 14,
    "sortie": 495,
    "fmizonmax": 300,
    "entree": 562,
    "etablissement_etalib": "Piscine Grand Parc",
    "fmicourante": 67,
    "datemiseajour": "2025-10-15T16:05:00+00:00"
  },
  "2025-10-15T16:25:00+00:00": {
    "fmizonlib": "Zone G\u00e9n\u00e9rale",
    "fmizonnum": 14,
    "sortie": 498,
    "fmizonmax": 300,
    "entree": 574,
    "etablissement_etalib": "Piscine Grand Parc",
    "fmicourante": 76,
    "datemiseajour": "2025-10-15T16:25:00+00:00"
  },
  "2025-10-15T16:50:00+00:00": {
    "fmizonlib": "Zone G\u00e9n\u00e9rale",
    "fmizonnum": 14,
    "sortie": 505,
    "fmizonmax": 300,
    "entree": 597,
    "etablissement_etalib": "Piscine Grand Parc",
    "fmicourante": 92,
    "datemiseajour": "2025-10-15T16:50:00+00:00"
  },
  "2025-10-15T17:10:00+00:00": {
    "fmizonlib": "Zone G\u00e9n\u00e9rale",
    "fmizonnum": 14,
    "sortie": 516,
    "fmizonmax": 300,
    "entree": 597,
    "etablissement_etalib": "Piscine Grand Parc",
    "fmicourante": 81,
    "datemiseajour": "2025-10-15T17:10:00+00:00"
  },
  "2025-10-15T17:25:00+00:00": {
    "fmizonlib": "Zone G\u00e9n\u00e9rale",
    "fmizonnum": 14,
    "sortie": 517,
    "fmizonmax": 300,
    "entree": 597,
    "etablissement_etalib": "Piscine Grand Parc",
    "fmicourante": 80,
    "datemiseajour": "2025-10-15T17:25:00+00:00"
  },
  "2025-10-15T17:35:00+00:00": {
    "fmizonlib": "Zone G\u00e9n\u00e9rale",
    "fmizonnum": 14,
    "sortie": 519,
    "fmizonmax": 300,
    "entree": 597,
    "etablissement_etalib": "Piscine Grand Parc",
    "fmicourante": 78,
    "datemiseajour": "2025-10-15T17:35:00+00:00"
  },
  "2025-10-15T17:45:00+00:00": {
    "fmizonlib": "Zone G\u00e9n\u00e9rale",
    "fmizonnum": 14,
    "sortie": 528,
    "fmizonmax": 300,
    "entree": 597,
    "etablissement_etalib": "Piscine Grand Parc",
    "fmicourante": 69,
    "datemiseajour": "2025-10-15T17:45:00+00:00"
  }
}